wikiserver.py
pysimplewiki-0.1.2.dist-info/entry_points.txt
pysimplewiki-0.1.2.dist-info/LICENSE
pysimplewiki-0.1.2.dist-info/WHEEL
pysimplewiki-0.1.2.dist-info/METADATA
pysimplewiki-0.1.2.dist-info/RECORD
