Metadata-Version: 2.1
Name: pysimplewiki
Version: 0.1.2
Summary: Simple Wiki - это вики движок, отображающий файловую структуру в веб-энциклопедию; поддерживает статьи в форматах .html, .md. Simple Wiki написана на языке python, поддерживает гибкое расширение и стилизацию.
Home-page: https://github.com/baterflyrity/pysimplewiki
Keywords: wiki, engine, markdown, web, server
Author: baterflyrity
Author-email: baterflyrity@yandex.ru
Requires-Python: ~=3.8
Classifier: License :: OSI Approved :: MIT License
Requires-Dist: typer[all] == 0.3.2
Requires-Dist: Markdown == 3.3.4
Requires-Dist: Jinja2 == 2.11.3
Requires-Dist: chardet == 4.0.0
Requires-Dist: python-markdown-math == 0.8
Requires-Dist: attributedict == 0.3.0
Project-URL: Bugtracker, https://github.com/baterflyrity/pysimplewiki/issues
